{
	"name": "FinalMonster",
	"plugin-id": "Sprite",
	"sid": 900730094822275,
	"isGlobal": false,
	"instanceVariables": [
		{
			"name": "direction2",
			"type": "string",
			"desc": "Right | Left",
			"show": true,
			"sid": 223912569973262
		},
		{
			"name": "health",
			"type": "number",
			"desc": "",
			"show": true,
			"sid": 730007367385204
		}
	],
	"behaviorTypes": [
		{
			"behaviorId": "LOS",
			"name": "LineOfSight",
			"sid": 567544424786821
		},
		{
			"behaviorId": "Platform",
			"name": "Platform",
			"sid": 769345524759556
		},
		{
			"behaviorId": "Flash",
			"name": "Flash",
			"sid": 291643014551273
		},
		{
			"behaviorId": "destroy",
			"name": "DestroyOutsideLayout",
			"sid": 981637495533917
		}
	],
	"effectTypes": [],
	"animations": {
		"items": [
			{
				"frames": [
					{
						"width": 631,
						"height": 495,
						"originX": 0.5,
						"originY": 0.5,
						"originalSource": "",
						"exportFormat": "lossless",
						"exportQuality": 0.8,
						"fileType": "image/png",
						"imageSpriteId": 15995,
						"collisionPoly": {
							"points": [
								0.3819629606929993,
								0.4230880638271691,
								0.42799130152364084,
								0.3881673845531087,
								0.5373216159289426,
								0.4043290866204781,
								0.6126859423235278,
								0.661183252793729,
								0.6366579795670306,
								0.806349210202436,
								0.5921875,
								0.953968253968254,
								0.340625,
								0.946897533691478,
								0.332634233282363,
								0.7939393401518109,
								0.30522465522907394,
								0.626695624726443,
								0.33281241052529825,
								0.4333333718105837
							]
						},
						"useCollisionPoly": true,
						"duration": 1,
						"tag": ""
					},
					{
						"width": 631,
						"height": 495,
						"originX": 0.5,
						"originY": 0.5,
						"originalSource": "",
						"exportFormat": "lossless",
						"exportQuality": 0.8,
						"fileType": "image/png",
						"imageSpriteId": 905228,
						"collisionPoly": {
							"points": [
								0.3819629606929993,
								0.4230880638271691,
								0.42799130152364084,
								0.3881673845531087,
								0.5373216159289426,
								0.4043290866204781,
								0.6126859423235278,
								0.661183252793729,
								0.6366579795670306,
								0.806349210202436,
								0.5921875,
								0.953968253968254,
								0.340625,
								0.946897533691478,
								0.332634233282363,
								0.7939393401518109,
								0.30522465522907394,
								0.626695624726443,
								0.33281241052529825,
								0.4333333718105837
							]
						},
						"useCollisionPoly": true,
						"duration": 1,
						"tag": ""
					},
					{
						"width": 631,
						"height": 495,
						"originX": 0.5,
						"originY": 0.5,
						"originalSource": "",
						"exportFormat": "lossless",
						"exportQuality": 0.8,
						"fileType": "image/png",
						"imageSpriteId": 8085311,
						"collisionPoly": {
							"points": [
								0.3819629606929993,
								0.4230880638271691,
								0.42799130152364084,
								0.3881673845531087,
								0.5373216159289426,
								0.4043290866204781,
								0.6126859423235278,
								0.661183252793729,
								0.6366579795670306,
								0.806349210202436,
								0.5921875,
								0.953968253968254,
								0.340625,
								0.946897533691478,
								0.332634233282363,
								0.7939393401518109,
								0.30522465522907394,
								0.626695624726443,
								0.33281241052529825,
								0.4333333718105837
							]
						},
						"useCollisionPoly": true,
						"duration": 1,
						"tag": ""
					},
					{
						"width": 631,
						"height": 495,
						"originX": 0.5,
						"originY": 0.5,
						"originalSource": "",
						"exportFormat": "lossless",
						"exportQuality": 0.8,
						"fileType": "image/png",
						"imageSpriteId": 3294752,
						"collisionPoly": {
							"points": [
								0.3819629606929993,
								0.4230880638271691,
								0.42799130152364084,
								0.3881673845531087,
								0.5373216159289426,
								0.4043290866204781,
								0.6126859423235278,
								0.661183252793729,
								0.6366579795670306,
								0.806349210202436,
								0.5921875,
								0.953968253968254,
								0.340625,
								0.946897533691478,
								0.332634233282363,
								0.7939393401518109,
								0.30522465522907394,
								0.626695624726443,
								0.33281241052529825,
								0.4333333718105837
							]
						},
						"useCollisionPoly": true,
						"duration": 1,
						"tag": ""
					},
					{
						"width": 631,
						"height": 495,
						"originX": 0.5,
						"originY": 0.5,
						"originalSource": "",
						"exportFormat": "lossless",
						"exportQuality": 0.8,
						"fileType": "image/png",
						"imageSpriteId": 8398766,
						"collisionPoly": {
							"points": [
								0.3819629606929993,
								0.4230880638271691,
								0.42799130152364084,
								0.3881673845531087,
								0.5373216159289426,
								0.4043290866204781,
								0.6126859423235278,
								0.661183252793729,
								0.6366579795670306,
								0.806349210202436,
								0.5921875,
								0.953968253968254,
								0.340625,
								0.946897533691478,
								0.332634233282363,
								0.7939393401518109,
								0.30522465522907394,
								0.626695624726443,
								0.33281241052529825,
								0.4333333718105837
							]
						},
						"useCollisionPoly": true,
						"duration": 1,
						"tag": ""
					},
					{
						"width": 631,
						"height": 495,
						"originX": 0.5,
						"originY": 0.5,
						"originalSource": "",
						"exportFormat": "lossless",
						"exportQuality": 0.8,
						"fileType": "image/png",
						"imageSpriteId": 3940486,
						"collisionPoly": {
							"points": [
								0.3819629606929993,
								0.4230880638271691,
								0.42799130152364084,
								0.3881673845531087,
								0.5373216159289426,
								0.4043290866204781,
								0.6126859423235278,
								0.661183252793729,
								0.6366579795670306,
								0.806349210202436,
								0.5921875,
								0.953968253968254,
								0.340625,
								0.946897533691478,
								0.332634233282363,
								0.7939393401518109,
								0.30522465522907394,
								0.626695624726443,
								0.33281241052529825,
								0.4333333718105837
							]
						},
						"useCollisionPoly": true,
						"duration": 1,
						"tag": ""
					}
				],
				"sid": 596105049886333,
				"name": "Idle",
				"isLooping": false,
				"isPingPong": false,
				"repeatCount": 1,
				"repeatTo": 0,
				"speed": 5
			},
			{
				"frames": [
					{
						"width": 746,
						"height": 630,
						"originX": 0.5,
						"originY": 0.5,
						"originalSource": "",
						"exportFormat": "lossless",
						"exportQuality": 0.8,
						"fileType": "image/png",
						"imageSpriteId": 7578619,
						"collisionPoly": {
							"points": [
								0.39291242217476197,
								0.5777778342000687,
								0.7565347912638472,
								0.4571429061063965,
								0.9199731952177148,
								0.4793650602365464,
								0.9086837967866341,
								0.5999999541740902,
								0.6265248744103684,
								0.7428571162698583,
								0.610954289165556,
								0.9222223184153479,
								0.35671074214342957,
								0.8793650867137388,
								0.15496390461235152,
								0.9428571717150805,
								0.1287950988082615,
								0.7444444763299197,
								0.1773165431459261,
								0.6428571858756993
							]
						},
						"useCollisionPoly": true,
						"duration": 1,
						"tag": ""
					},
					{
						"width": 746,
						"height": 630,
						"originX": 0.5,
						"originY": 0.5,
						"originalSource": "",
						"exportFormat": "lossless",
						"exportQuality": 0.8,
						"fileType": "image/png",
						"imageSpriteId": 1869786,
						"collisionPoly": {
							"points": [
								0.39291242217476197,
								0.5777778342000687,
								0.7565347912638472,
								0.4571429061063965,
								0.9199731952177148,
								0.4793650602365464,
								0.9086837967866341,
								0.5999999541740902,
								0.6265248744103684,
								0.7428571162698583,
								0.610954289165556,
								0.9222223184153479,
								0.35671074214342957,
								0.8793650867137388,
								0.15496390461235152,
								0.9428571717150805,
								0.1287950988082615,
								0.7444444763299197,
								0.1773165431459261,
								0.6428571858756993
							]
						},
						"useCollisionPoly": true,
						"duration": 1,
						"tag": ""
					},
					{
						"width": 746,
						"height": 630,
						"originX": 0.5,
						"originY": 0.5,
						"originalSource": "",
						"exportFormat": "lossless",
						"exportQuality": 0.8,
						"fileType": "image/png",
						"imageSpriteId": 9970479,
						"collisionPoly": {
							"points": [
								0.39291242217476197,
								0.5777778342000687,
								0.7565347912638472,
								0.4571429061063965,
								0.9199731952177148,
								0.4793650602365464,
								0.9086837967866341,
								0.5999999541740902,
								0.6265248744103684,
								0.7428571162698583,
								0.610954289165556,
								0.9222223184153479,
								0.35671074214342957,
								0.8793650867137388,
								0.15496390461235152,
								0.9428571717150805,
								0.1287950988082615,
								0.7444444763299197,
								0.1773165431459261,
								0.6428571858756993
							]
						},
						"useCollisionPoly": true,
						"duration": 1,
						"tag": ""
					},
					{
						"width": 746,
						"height": 630,
						"originX": 0.5,
						"originY": 0.5,
						"originalSource": "",
						"exportFormat": "lossless",
						"exportQuality": 0.8,
						"fileType": "image/png",
						"imageSpriteId": 6927484,
						"collisionPoly": {
							"points": [
								0.39291242217476197,
								0.5777778342000687,
								0.7565347912638472,
								0.4571429061063965,
								0.9199731952177148,
								0.4793650602365464,
								0.9086837967866341,
								0.5999999541740902,
								0.6265248744103684,
								0.7428571162698583,
								0.610954289165556,
								0.9222223184153479,
								0.35671074214342957,
								0.8793650867137388,
								0.15496390461235152,
								0.9428571717150805,
								0.1287950988082615,
								0.7444444763299197,
								0.1773165431459261,
								0.6428571858756993
							]
						},
						"useCollisionPoly": true,
						"duration": 1,
						"tag": ""
					},
					{
						"width": 746,
						"height": 630,
						"originX": 0.5,
						"originY": 0.5,
						"originalSource": "",
						"exportFormat": "lossless",
						"exportQuality": 0.8,
						"fileType": "image/png",
						"imageSpriteId": 9351176,
						"collisionPoly": {
							"points": [
								0.39291242217476197,
								0.5777778342000687,
								0.7565347912638472,
								0.4571429061063965,
								0.9199731952177148,
								0.4793650602365464,
								0.9086837967866341,
								0.5999999541740902,
								0.6265248744103684,
								0.7428571162698583,
								0.610954289165556,
								0.9222223184153479,
								0.35671074214342957,
								0.8793650867137388,
								0.15496390461235152,
								0.9428571717150805,
								0.1287950988082615,
								0.7444444763299197,
								0.1773165431459261,
								0.6428571858756993
							]
						},
						"useCollisionPoly": true,
						"duration": 1,
						"tag": ""
					}
				],
				"sid": 929866155764034,
				"name": "Attack1",
				"isLooping": false,
				"isPingPong": false,
				"repeatCount": 1,
				"repeatTo": 0,
				"speed": 5
			},
			{
				"frames": [
					{
						"width": 640,
						"height": 630,
						"originX": 0.5,
						"originY": 0.5,
						"originalSource": "",
						"exportFormat": "lossless",
						"exportQuality": 0.8,
						"fileType": "image/png",
						"imageSpriteId": 556803,
						"collisionPoly": {
							"points": [
								0.44062494393099305,
								0.51428569667095,
								0.5375000022351742,
								0.5269841241767738,
								0.9156249120154147,
								0.4571429586341734,
								0.9140625568140649,
								0.6158730285198658,
								0.5281250296804045,
								0.8000000134037343,
								0.5921875,
								0.953968253968254,
								0.340625,
								0.9873015873015873,
								0.3453124832971527,
								0.9460317652703711,
								0.26249994765628326,
								0.7222223214428855,
								0.3234373340281536,
								0.484126975264556
							]
						},
						"useCollisionPoly": true,
						"duration": 1,
						"tag": ""
					},
					{
						"width": 640,
						"height": 630,
						"originX": 0.5,
						"originY": 0.5,
						"originalSource": "",
						"exportFormat": "lossless",
						"exportQuality": 0.8,
						"fileType": "image/png",
						"imageSpriteId": 454035,
						"collisionPoly": {
							"points": [
								0.44062494393099305,
								0.51428569667095,
								0.5375000022351742,
								0.5269841241767738,
								0.9156249120154147,
								0.4571429586341734,
								0.9140625568140649,
								0.6158730285198658,
								0.5281250296804045,
								0.8000000134037343,
								0.5921875,
								0.953968253968254,
								0.340625,
								0.9873015873015873,
								0.3453124832971527,
								0.9460317652703711,
								0.26249994765628326,
								0.7222223214428855,
								0.3234373340281536,
								0.484126975264556
							]
						},
						"useCollisionPoly": true,
						"duration": 1,
						"tag": ""
					},
					{
						"width": 640,
						"height": 630,
						"originX": 0.5,
						"originY": 0.5,
						"originalSource": "",
						"exportFormat": "lossless",
						"exportQuality": 0.8,
						"fileType": "image/png",
						"imageSpriteId": 5789250,
						"collisionPoly": {
							"points": [
								0.44062494393099305,
								0.51428569667095,
								0.5375000022351742,
								0.5269841241767738,
								0.9156249120154147,
								0.4571429586341734,
								0.9140625568140649,
								0.6158730285198658,
								0.5281250296804045,
								0.8000000134037343,
								0.5921875,
								0.953968253968254,
								0.340625,
								0.9873015873015873,
								0.3453124832971527,
								0.9460317652703711,
								0.26249994765628326,
								0.7222223214428855,
								0.3234373340281536,
								0.484126975264556
							]
						},
						"useCollisionPoly": true,
						"duration": 1,
						"tag": ""
					},
					{
						"width": 640,
						"height": 630,
						"originX": 0.5,
						"originY": 0.5,
						"originalSource": "",
						"exportFormat": "lossless",
						"exportQuality": 0.8,
						"fileType": "image/png",
						"imageSpriteId": 1825713,
						"collisionPoly": {
							"points": [
								0.44062494393099305,
								0.51428569667095,
								0.5375000022351742,
								0.5269841241767738,
								0.9156249120154147,
								0.4571429586341734,
								0.9140625568140649,
								0.6158730285198658,
								0.5281250296804045,
								0.8000000134037343,
								0.5921875,
								0.953968253968254,
								0.340625,
								0.9873015873015873,
								0.3453124832971527,
								0.9460317652703711,
								0.26249994765628326,
								0.7222223214428855,
								0.3234373340281536,
								0.484126975264556
							]
						},
						"useCollisionPoly": true,
						"duration": 1,
						"tag": ""
					},
					{
						"width": 640,
						"height": 630,
						"originX": 0.5,
						"originY": 0.5,
						"originalSource": "",
						"exportFormat": "lossless",
						"exportQuality": 0.8,
						"fileType": "image/png",
						"imageSpriteId": 3836586,
						"collisionPoly": {
							"points": [
								0.44062494393099305,
								0.51428569667095,
								0.5375000022351742,
								0.5269841241767738,
								0.9156249120154147,
								0.4571429586341734,
								0.9140625568140649,
								0.6158730285198658,
								0.5281250296804045,
								0.8000000134037343,
								0.5921875,
								0.953968253968254,
								0.340625,
								0.9873015873015873,
								0.3453124832971527,
								0.9460317652703711,
								0.26249994765628326,
								0.7222223214428855,
								0.3234373340281536,
								0.484126975264556
							]
						},
						"useCollisionPoly": true,
						"duration": 1,
						"tag": ""
					}
				],
				"sid": 433624274708130,
				"name": "Attack2",
				"isLooping": false,
				"isPingPong": false,
				"repeatCount": 1,
				"repeatTo": 0,
				"speed": 5
			},
			{
				"frames": [
					{
						"width": 815,
						"height": 590,
						"originX": 0.5,
						"originY": 0.5,
						"originalSource": "",
						"exportFormat": "lossless",
						"exportQuality": 0.8,
						"fileType": "image/png",
						"imageSpriteId": 6102766,
						"collisionPoly": {
							"points": [
								0.3950536130424375,
								0.33656168533886927,
								0.5135737316938721,
								0.3359160585783865,
								0.7070550990496915,
								0.2748991228638659,
								0.8984566111226875,
								0.5641108128789329,
								0.8181365607985569,
								0.7133171620852821,
								0.5529238152916206,
								0.8488834852380078,
								0.41424457358569194,
								0.8313694012219011,
								0.2324290602456008,
								0.8477266370141353,
								0.17199007302398087,
								0.6526500978900678,
								0.33281241052529825,
								0.4333333718105837
							]
						},
						"useCollisionPoly": true,
						"duration": 1,
						"tag": ""
					},
					{
						"width": 815,
						"height": 590,
						"originX": 0.5,
						"originY": 0.5,
						"originalSource": "",
						"exportFormat": "lossless",
						"exportQuality": 0.8,
						"fileType": "image/png",
						"imageSpriteId": 519311,
						"collisionPoly": {
							"points": [
								0.3950536130424375,
								0.33656168533886927,
								0.5135737316938721,
								0.3359160585783865,
								0.7070550990496915,
								0.2748991228638659,
								0.8984566111226875,
								0.5641108128789329,
								0.8181365607985569,
								0.7133171620852821,
								0.5529238152916206,
								0.8488834852380078,
								0.41424457358569194,
								0.8313694012219011,
								0.2324290602456008,
								0.8477266370141353,
								0.17199007302398087,
								0.6526500978900678,
								0.33281241052529825,
								0.4333333718105837
							]
						},
						"useCollisionPoly": true,
						"duration": 1,
						"tag": ""
					},
					{
						"width": 815,
						"height": 590,
						"originX": 0.5,
						"originY": 0.5,
						"originalSource": "",
						"exportFormat": "lossless",
						"exportQuality": 0.8,
						"fileType": "image/png",
						"imageSpriteId": 9655336,
						"collisionPoly": {
							"points": [
								0.3950536130424375,
								0.33656168533886927,
								0.5135737316938721,
								0.3359160585783865,
								0.7070550990496915,
								0.2748991228638659,
								0.8984566111226875,
								0.5641108128789329,
								0.8181365607985569,
								0.7133171620852821,
								0.5529238152916206,
								0.8488834852380078,
								0.41424457358569194,
								0.8313694012219011,
								0.2324290602456008,
								0.8477266370141353,
								0.17199007302398087,
								0.6526500978900678,
								0.33281241052529825,
								0.4333333718105837
							]
						},
						"useCollisionPoly": true,
						"duration": 1,
						"tag": ""
					},
					{
						"width": 815,
						"height": 590,
						"originX": 0.5,
						"originY": 0.5,
						"originalSource": "",
						"exportFormat": "lossless",
						"exportQuality": 0.8,
						"fileType": "image/png",
						"imageSpriteId": 6975920,
						"collisionPoly": {
							"points": [
								0.3950536130424375,
								0.33656168533886927,
								0.5135737316938721,
								0.3359160585783865,
								0.7070550990496915,
								0.2748991228638659,
								0.8984566111226875,
								0.5641108128789329,
								0.8181365607985569,
								0.7133171620852821,
								0.5529238152916206,
								0.8488834852380078,
								0.41424457358569194,
								0.8313694012219011,
								0.2324290602456008,
								0.8477266370141353,
								0.17199007302398087,
								0.6526500978900678,
								0.33281241052529825,
								0.4333333718105837
							]
						},
						"useCollisionPoly": true,
						"duration": 1,
						"tag": ""
					},
					{
						"width": 815,
						"height": 590,
						"originX": 0.5,
						"originY": 0.5,
						"originalSource": "",
						"exportFormat": "lossless",
						"exportQuality": 0.8,
						"fileType": "image/png",
						"imageSpriteId": 6560109,
						"collisionPoly": {
							"points": [
								0.3950536130424375,
								0.33656168533886927,
								0.5135737316938721,
								0.3359160585783865,
								0.7070550990496915,
								0.2748991228638659,
								0.8984566111226875,
								0.5641108128789329,
								0.8181365607985569,
								0.7133171620852821,
								0.5529238152916206,
								0.8488834852380078,
								0.41424457358569194,
								0.8313694012219011,
								0.2324290602456008,
								0.8477266370141353,
								0.17199007302398087,
								0.6526500978900678,
								0.33281241052529825,
								0.4333333718105837
							]
						},
						"useCollisionPoly": true,
						"duration": 1,
						"tag": ""
					}
				],
				"sid": 676091248205588,
				"name": "Die",
				"isLooping": false,
				"isPingPong": false,
				"repeatCount": 1,
				"repeatTo": 0,
				"speed": 5
			},
			{
				"frames": [
					{
						"width": 677,
						"height": 516,
						"originX": 0.5,
						"originY": 0.5,
						"originalSource": "",
						"exportFormat": "lossless",
						"exportQuality": 0.8,
						"fileType": "image/png",
						"imageSpriteId": 1878676,
						"collisionPoly": {
							"points": [
								0.33124996063384043,
								0.28571426798942934,
								0.43750009543516627,
								0.2952381019399624,
								0.5499998659437323,
								0.295238101183078,
								0.9328125,
								0.4793650793650794,
								0.91875,
								0.6285714285714286,
								0.5921875,
								0.953968253968254,
								0.340625,
								0.9873015873015873,
								0.3453124832971527,
								0.9460317652703711,
								0.041345029404330325,
								0.6991878951778788,
								0.33281241052529825,
								0.4333333718105837
							]
						},
						"useCollisionPoly": true,
						"duration": 1,
						"tag": ""
					},
					{
						"width": 677,
						"height": 516,
						"originX": 0.5,
						"originY": 0.5,
						"originalSource": "",
						"exportFormat": "lossless",
						"exportQuality": 0.8,
						"fileType": "image/png",
						"imageSpriteId": 9851741,
						"collisionPoly": {
							"points": [
								0.33124996063384043,
								0.28571426798942934,
								0.43750009543516627,
								0.2952381019399624,
								0.5499998659437323,
								0.295238101183078,
								0.9328125,
								0.4793650793650794,
								0.91875,
								0.6285714285714286,
								0.5921875,
								0.953968253968254,
								0.340625,
								0.9873015873015873,
								0.3453124832971527,
								0.9460317652703711,
								0.041345029404330325,
								0.6991878951778788,
								0.33281241052529825,
								0.4333333718105837
							]
						},
						"useCollisionPoly": true,
						"duration": 1,
						"tag": ""
					},
					{
						"width": 677,
						"height": 516,
						"originX": 0.5,
						"originY": 0.5,
						"originalSource": "",
						"exportFormat": "lossless",
						"exportQuality": 0.8,
						"fileType": "image/png",
						"imageSpriteId": 9507214,
						"collisionPoly": {
							"points": [
								0.33124996063384043,
								0.28571426798942934,
								0.43750009543516627,
								0.2952381019399624,
								0.5499998659437323,
								0.295238101183078,
								0.9328125,
								0.4793650793650794,
								0.91875,
								0.6285714285714286,
								0.5921875,
								0.953968253968254,
								0.340625,
								0.9873015873015873,
								0.3453124832971527,
								0.9460317652703711,
								0.041345029404330325,
								0.6991878951778788,
								0.33281241052529825,
								0.4333333718105837
							]
						},
						"useCollisionPoly": true,
						"duration": 1,
						"tag": ""
					},
					{
						"width": 677,
						"height": 516,
						"originX": 0.5,
						"originY": 0.5,
						"originalSource": "",
						"exportFormat": "lossless",
						"exportQuality": 0.8,
						"fileType": "image/png",
						"imageSpriteId": 8745671,
						"collisionPoly": {
							"points": [
								0.33124996063384043,
								0.28571426798942934,
								0.43750009543516627,
								0.2952381019399624,
								0.5499998659437323,
								0.295238101183078,
								0.9328125,
								0.4793650793650794,
								0.91875,
								0.6285714285714286,
								0.5921875,
								0.953968253968254,
								0.340625,
								0.9873015873015873,
								0.3453124832971527,
								0.9460317652703711,
								0.041345029404330325,
								0.6991878951778788,
								0.33281241052529825,
								0.4333333718105837
							]
						},
						"useCollisionPoly": true,
						"duration": 1,
						"tag": ""
					},
					{
						"width": 677,
						"height": 516,
						"originX": 0.5,
						"originY": 0.5,
						"originalSource": "",
						"exportFormat": "lossless",
						"exportQuality": 0.8,
						"fileType": "image/png",
						"imageSpriteId": 8337485,
						"collisionPoly": {
							"points": [
								0.33124996063384043,
								0.28571426798942934,
								0.43750009543516627,
								0.2952381019399624,
								0.5499998659437323,
								0.295238101183078,
								0.9328125,
								0.4793650793650794,
								0.91875,
								0.6285714285714286,
								0.5921875,
								0.953968253968254,
								0.340625,
								0.9873015873015873,
								0.3453124832971527,
								0.9460317652703711,
								0.041345029404330325,
								0.6991878951778788,
								0.33281241052529825,
								0.4333333718105837
							]
						},
						"useCollisionPoly": true,
						"duration": 1,
						"tag": ""
					},
					{
						"width": 677,
						"height": 516,
						"originX": 0.5,
						"originY": 0.5,
						"originalSource": "",
						"exportFormat": "lossless",
						"exportQuality": 0.8,
						"fileType": "image/png",
						"imageSpriteId": 5334044,
						"collisionPoly": {
							"points": [
								0.33124996063384043,
								0.28571426798942934,
								0.43750009543516627,
								0.2952381019399624,
								0.5499998659437323,
								0.295238101183078,
								0.9328125,
								0.4793650793650794,
								0.91875,
								0.6285714285714286,
								0.5921875,
								0.953968253968254,
								0.340625,
								0.9873015873015873,
								0.3453124832971527,
								0.9460317652703711,
								0.041345029404330325,
								0.6991878951778788,
								0.33281241052529825,
								0.4333333718105837
							]
						},
						"useCollisionPoly": true,
						"duration": 1,
						"tag": ""
					},
					{
						"width": 677,
						"height": 516,
						"originX": 0.5,
						"originY": 0.5,
						"originalSource": "",
						"exportFormat": "lossless",
						"exportQuality": 0.8,
						"fileType": "image/png",
						"imageSpriteId": 249348,
						"collisionPoly": {
							"points": [
								0.33124996063384043,
								0.28571426798942934,
								0.43750009543516627,
								0.2952381019399624,
								0.5499998659437323,
								0.295238101183078,
								0.9328125,
								0.4793650793650794,
								0.91875,
								0.6285714285714286,
								0.5921875,
								0.953968253968254,
								0.340625,
								0.9873015873015873,
								0.3453124832971527,
								0.9460317652703711,
								0.041345029404330325,
								0.6991878951778788,
								0.33281241052529825,
								0.4333333718105837
							]
						},
						"useCollisionPoly": true,
						"duration": 1,
						"tag": ""
					}
				],
				"sid": 808235399991695,
				"name": "Walk",
				"isLooping": false,
				"isPingPong": false,
				"repeatCount": 1,
				"repeatTo": 0,
				"speed": 5
			},
			{
				"frames": [
					{
						"width": 714,
						"height": 558,
						"originX": 0.5,
						"originY": 0.5,
						"originalSource": "",
						"exportFormat": "lossless",
						"exportQuality": 0.8,
						"fileType": "image/png",
						"imageSpriteId": 1021772,
						"collisionPoly": {
							"points": [
								0.5140056022408963,
								0.06451612903225806,
								0.5602240896358543,
								0.06451612903225806,
								0.6946778711484594,
								0.11290322580645161,
								0.9537815126050421,
								0.6397849462365591,
								0.8753501400560224,
								0.7777777777777778,
								0.7002801120448179,
								0.9032258064516129,
								0.47619047619047616,
								0.942652329749104,
								0.15126050420168066,
								0.8781362007168458,
								0.1400560224089636,
								0.600358422939068,
								0.18067226890756302,
								0.33691756272401435,
								0.22128851540616246,
								0.26523297491039427
							]
						},
						"useCollisionPoly": true,
						"duration": 1,
						"tag": ""
					},
					{
						"width": 714,
						"height": 558,
						"originX": 0.5,
						"originY": 0.5,
						"originalSource": "",
						"exportFormat": "lossless",
						"exportQuality": 0.8,
						"fileType": "image/png",
						"imageSpriteId": 2856241,
						"collisionPoly": {
							"points": [
								0.4957983193277311,
								0.07706093189964158,
								0.6414565826330533,
								0.08422939068100359,
								0.6792717086834734,
								0.13978494623655913,
								0.9047619047619048,
								0.6989247311827957,
								0.8263305322128851,
								0.8064516129032258,
								0.6890756302521008,
								0.9032258064516129,
								0.4677871148459384,
								0.9516129032258065,
								0.22268907563025211,
								0.9408602150537635,
								0.07983193277310924,
								0.8637992831541219,
								0.10224089635854341,
								0.5878136200716846,
								0.17366946778711484,
								0.33512544802867383,
								0.2184873949579832,
								0.27419354838709675
							]
						},
						"useCollisionPoly": true,
						"duration": 1,
						"tag": ""
					},
					{
						"width": 714,
						"height": 558,
						"originX": 0.5,
						"originY": 0.5,
						"originalSource": "",
						"exportFormat": "lossless",
						"exportQuality": 0.8,
						"fileType": "image/png",
						"imageSpriteId": 5429808,
						"collisionPoly": {
							"points": [
								0.5910364145658263,
								0.07168458781362007,
								0.6330532212885154,
								0.11290322580645161,
								0.7310924369747899,
								0.2849462365591398,
								0.8599439775910365,
								0.7365591397849462,
								0.7801120448179272,
								0.8279569892473119,
								0.680672268907563,
								0.9014336917562724,
								0.542016806722689,
								0.9551971326164874,
								0.46078431372549017,
								0.9605734767025089,
								0.15266106442577032,
								0.946236559139785,
								0.01680672268907563,
								0.8637992831541219,
								0.01680672268907563,
								0.8225806451612904,
								0.07142857142857142,
								0.5698924731182796,
								0.17787114845938376,
								0.32974910394265233,
								0.4103641456582633,
								0.12007168458781362,
								0.44677871148459386,
								0.0985663082437276
							]
						},
						"useCollisionPoly": true,
						"duration": 1,
						"tag": ""
					},
					{
						"width": 714,
						"height": 558,
						"originX": 0.5,
						"originY": 0.5,
						"originalSource": "",
						"exportFormat": "lossless",
						"exportQuality": 0.8,
						"fileType": "image/png",
						"imageSpriteId": 1583762,
						"collisionPoly": {
							"points": [
								0.6064425770308123,
								0.07526881720430108,
								0.6498599439775911,
								0.12544802867383512,
								0.7338935574229691,
								0.27956989247311825,
								0.8753501400560224,
								0.7222222222222222,
								0.7927170868347339,
								0.8225806451612904,
								0.680672268907563,
								0.9032258064516129,
								0.5448179271708683,
								0.9516129032258065,
								0.5028011204481793,
								0.956989247311828,
								0.46078431372549017,
								0.956989247311828,
								0.17366946778711484,
								0.946236559139785,
								0.03361344537815126,
								0.8620071684587813,
								0.0784313725490196,
								0.578853046594982,
								0.16806722689075632,
								0.34050179211469533,
								0.21708683473389356,
								0.2849462365591398,
								0.46078431372549017,
								0.0913978494623656
							]
						},
						"useCollisionPoly": true,
						"duration": 1,
						"tag": ""
					},
					{
						"width": 714,
						"height": 558,
						"originX": 0.5,
						"originY": 0.5,
						"originalSource": "",
						"exportFormat": "lossless",
						"exportQuality": 0.8,
						"fileType": "image/png",
						"imageSpriteId": 7565965,
						"collisionPoly": {
							"points": [
								0.6260504201680672,
								0.07885304659498207,
								0.6666666666666666,
								0.13261648745519714,
								0.8921568627450981,
								0.7096774193548387,
								0.8123249299719888,
								0.8136200716845878,
								0.6862745098039216,
								0.9032258064516129,
								0.5476190476190477,
								0.946236559139785,
								0.4635854341736695,
								0.953405017921147,
								0.20588235294117646,
								0.9444444444444444,
								0.06162464985994398,
								0.8709677419354839,
								0.09243697478991597,
								0.5824372759856631,
								0.16526610644257703,
								0.34767025089605735,
								0.21988795518207283,
								0.27598566308243727,
								0.49159663865546216,
								0.08064516129032258
							]
						},
						"useCollisionPoly": true,
						"duration": 1,
						"tag": ""
					},
					{
						"width": 714,
						"height": 558,
						"originX": 0.5,
						"originY": 0.5,
						"originalSource": "",
						"exportFormat": "lossless",
						"exportQuality": 0.8,
						"fileType": "image/png",
						"imageSpriteId": 5074478,
						"collisionPoly": {
							"points": [
								0.5084033613445378,
								0.07347670250896057,
								0.65406162464986,
								0.09498207885304659,
								0.6848739495798319,
								0.14336917562724014,
								0.9117647058823529,
								0.6917562724014337,
								0.8305322128851541,
								0.8046594982078853,
								0.6904761904761905,
								0.9032258064516129,
								0.4677871148459384,
								0.9498207885304659,
								0.08823529411764706,
								0.8566308243727598,
								0.10644257703081232,
								0.5913978494623656,
								0.16946778711484595,
								0.34408602150537637,
								0.2184873949579832,
								0.2724014336917563,
								0.469187675070028,
								0.08243727598566308
							]
						},
						"useCollisionPoly": true,
						"duration": 1,
						"tag": ""
					},
					{
						"width": 714,
						"height": 558,
						"originX": 0.5,
						"originY": 0.5,
						"originalSource": "",
						"exportFormat": "lossless",
						"exportQuality": 0.8,
						"fileType": "image/png",
						"imageSpriteId": 4297260,
						"collisionPoly": {
							"points": [
								0.5350140056022409,
								0.06810035842293907,
								0.6736694677871149,
								0.10215053763440861,
								0.9341736694677871,
								0.6648745519713262,
								0.8543417366946778,
								0.7903225806451613,
								0.6890756302521008,
								0.9050179211469535,
								0.47198879551820727,
								0.946236559139785,
								0.12044817927170869,
								0.8817204301075269,
								0.12324929971988796,
								0.5931899641577061,
								0.17787114845938376,
								0.3333333333333333,
								0.21708683473389356,
								0.27060931899641577
							]
						},
						"useCollisionPoly": true,
						"duration": 1,
						"tag": ""
					}
				],
				"sid": 600270993169058,
				"name": "Hurt",
				"isLooping": false,
				"isPingPong": false,
				"repeatCount": 1,
				"repeatTo": 0,
				"speed": 5
			}
		],
		"subfolders": []
	}
}